<?xml version="1.0" encoding="UTF-8"?>
<!DOCTYPE why3session PUBLIC "-//Why3//proof session v5//EN"
"http://why3.lri.fr/why3session.dtd">
<why3session shape_version="6">
<prover id="0" name="altergo" version="1.30-gnatprove" timelimit="180" steplimit="40000" memlimit="0"/>
<prover id="1" name="Z3" version="4.5.1-gnatprove" timelimit="180" steplimit="32450000" memlimit="0"/>
<prover id="2" name="CVC4" version="1.6-gnatprove" timelimit="180" steplimit="1415000" memlimit="0"/>
<prover id="3" name="CVC4_CE" version="1.6-gnatprove" timelimit="10" steplimit="1415000" memlimit="0"/>
<file>
<path name=".."/>
<path name=".."/>
<path name=".."/>
<path name="tlsf"/>
<path name="obj"/>
<path name="gnatprove"/>
<path name="tlsf-block-types.mlw"/>
<theory name="Tlsf__block__types__package_def">
 <goal name="VC def" expl="VC for def">
 <transf name="split_goal_wp_conj" >
  <goal name="VC def.0" expl="postcondition">
  </goal>
  <goal name="VC def.1" expl="precondition" proved="true">
  <proof prover="0"><result status="valid" steps="384"/></proof>
  </goal>
  <goal name="VC def.2" expl="precondition" proved="true">
  <proof prover="0"><result status="valid" steps="385"/></proof>
  </goal>
  <goal name="VC def.3" expl="postcondition">
  </goal>
  <goal name="VC def.4" expl="postcondition">
  </goal>
  <goal name="VC def.5" expl="postcondition">
  </goal>
  <goal name="VC def.6" expl="assertion" proved="true">
  <proof prover="0"><result status="failure"/></proof>
  <proof prover="1"><result status="valid" steps="7715"/></proof>
  </goal>
  <goal name="VC def.7" expl="assertion" proved="true">
  <proof prover="0"><result status="valid" steps="188"/></proof>
  </goal>
  <goal name="VC def.8" expl="assertion" proved="true">
  <proof prover="0"><result status="valid" steps="394"/></proof>
  </goal>
  <goal name="VC def.9" expl="postcondition">
  </goal>
  <goal name="VC def.10" expl="assertion" proved="true">
  <proof prover="0"><result status="valid" steps="196"/></proof>
  </goal>
  <goal name="VC def.11" expl="postcondition">
  </goal>
  <goal name="VC def.12" expl="assertion" proved="true">
  <proof prover="0"><result status="valid" steps="197"/></proof>
  </goal>
 </transf>
 </goal>
</theory>
<theory name="Tlsf__block__types__to_size_bits__subprogram_def">
 <goal name="VC def" expl="VC for def">
 <transf name="split_goal_wp_conj" >
  <goal name="VC def.0" expl="postcondition">
  </goal>
  <goal name="VC def.1" expl="postcondition">
  </goal>
  <goal name="VC def.2" expl="assertion" proved="true">
  <proof prover="0"><result status="valid" steps="659"/></proof>
  </goal>
  <goal name="VC def.3" expl="assertion" proved="true">
  <proof prover="0"><result status="valid" steps="661"/></proof>
  </goal>
  <goal name="VC def.4" expl="postcondition">
  </goal>
  <goal name="VC def.5" expl="assertion" proved="true">
  <proof prover="0"><result status="valid" steps="354"/></proof>
  </goal>
  <goal name="VC def.6" expl="postcondition">
  </goal>
  <goal name="VC def.7" expl="postcondition" proved="true">
  <proof prover="0"><result status="valid" steps="156"/></proof>
  </goal>
 </transf>
 </goal>
</theory>
<theory name="Tlsf__block__types__to_address_bits__subprogram_def">
 <goal name="VC def" expl="VC for def">
 <transf name="split_goal_wp_conj" >
  <goal name="VC def.0" expl="postcondition">
  </goal>
  <goal name="VC def.1" expl="postcondition">
  </goal>
  <goal name="VC def.2" expl="assertion" proved="true">
  <proof prover="0"><result status="valid" steps="659"/></proof>
  </goal>
  <goal name="VC def.3" expl="assertion" proved="true">
  <proof prover="0"><result status="valid" steps="660"/></proof>
  </goal>
  <goal name="VC def.4" expl="postcondition">
  </goal>
  <goal name="VC def.5" expl="assertion" proved="true">
  <proof prover="0"><result status="valid" steps="354"/></proof>
  </goal>
  <goal name="VC def.6" expl="postcondition">
  </goal>
  <goal name="VC def.7" expl="postcondition" proved="true">
  <proof prover="0"><result status="valid" steps="156"/></proof>
  </goal>
 </transf>
 </goal>
</theory>
<theory name="Tlsf__block__types__is_aligned__subprogram_def">
 <goal name="VC def" expl="VC for def">
 <transf name="split_goal_wp_conj" >
  <goal name="VC def.0" expl="postcondition">
  </goal>
  <goal name="VC def.1" expl="postcondition">
  </goal>
  <goal name="VC def.2" expl="postcondition">
  </goal>
  <goal name="VC def.3" expl="precondition" proved="true">
  <proof prover="0"><result status="valid" steps="155"/></proof>
  </goal>
  <goal name="VC def.4" expl="precondition" proved="true">
  <proof prover="0"><result status="valid" steps="355"/></proof>
  </goal>
  <goal name="VC def.5" expl="precondition" proved="true">
  <proof prover="0"><result status="valid" steps="697"/></proof>
  </goal>
  <goal name="VC def.6" expl="postcondition">
  </goal>
  <goal name="VC def.7" expl="postcondition">
  </goal>
  <goal name="VC def.8" expl="assertion" proved="true">
  <proof prover="0"><result status="valid" steps="155"/></proof>
  </goal>
  <goal name="VC def.9" expl="assertion" proved="true">
  <proof prover="0"><result status="valid" steps="156"/></proof>
  </goal>
  <goal name="VC def.10" expl="assertion" proved="true">
  <proof prover="0"><result status="valid" steps="155"/></proof>
  </goal>
  <goal name="VC def.11" expl="postcondition">
  </goal>
  <goal name="VC def.12" expl="assertion" proved="true">
  <proof prover="0"><result status="valid" steps="349"/></proof>
  </goal>
  <goal name="VC def.13" expl="assertion" proved="true">
  <proof prover="0"><result status="valid" steps="155"/></proof>
  </goal>
  <goal name="VC def.14" expl="assertion" proved="true">
  <proof prover="0"><result status="valid" steps="155"/></proof>
  </goal>
 </transf>
 </goal>
</theory>
<theory name="Tlsf__block__types__is_aligned__2__subprogram_def">
 <goal name="VC def" expl="VC for def">
 <transf name="split_goal_wp_conj" >
  <goal name="VC def.0" expl="postcondition">
  </goal>
  <goal name="VC def.1" expl="postcondition">
  </goal>
  <goal name="VC def.2" expl="postcondition">
  </goal>
  <goal name="VC def.3" expl="precondition" proved="true">
  <proof prover="0"><result status="valid" steps="155"/></proof>
  </goal>
  <goal name="VC def.4" expl="precondition" proved="true">
  <proof prover="0"><result status="valid" steps="355"/></proof>
  </goal>
  <goal name="VC def.5" expl="precondition" proved="true">
  <proof prover="0"><result status="valid" steps="696"/></proof>
  </goal>
  <goal name="VC def.6" expl="postcondition">
  </goal>
  <goal name="VC def.7" expl="postcondition">
  </goal>
  <goal name="VC def.8" expl="assertion" proved="true">
  <proof prover="0"><result status="valid" steps="155"/></proof>
  </goal>
  <goal name="VC def.9" expl="assertion" proved="true">
  <proof prover="0"><result status="valid" steps="156"/></proof>
  </goal>
  <goal name="VC def.10" expl="assertion" proved="true">
  <proof prover="0"><result status="valid" steps="155"/></proof>
  </goal>
  <goal name="VC def.11" expl="postcondition">
  </goal>
  <goal name="VC def.12" expl="assertion" proved="true">
  <proof prover="0"><result status="valid" steps="349"/></proof>
  </goal>
  <goal name="VC def.13" expl="assertion" proved="true">
  <proof prover="0"><result status="valid" steps="155"/></proof>
  </goal>
  <goal name="VC def.14" expl="assertion" proved="true">
  <proof prover="0"><result status="valid" steps="155"/></proof>
  </goal>
 </transf>
 </goal>
</theory>
<theory name="Tlsf__block__types__round_size_up__subprogram_def">
 <goal name="VC def" expl="VC for def">
 <transf name="split_goal_wp_conj" >
  <goal name="VC def.0" expl="postcondition">
  </goal>
  <goal name="VC def.1" expl="precondition" proved="true">
  <proof prover="0"><result status="valid" steps="155"/></proof>
  </goal>
  <goal name="VC def.2" expl="precondition" proved="true">
  <proof prover="0"><result status="valid" steps="155"/></proof>
  </goal>
  <goal name="VC def.3" expl="precondition" proved="true">
  <proof prover="0"><result status="valid" steps="155"/></proof>
  </goal>
  <goal name="VC def.4" expl="precondition" proved="true">
  <proof prover="0"><result status="valid" steps="668"/></proof>
  </goal>
  <goal name="VC def.5" expl="precondition" proved="true">
  <proof prover="0"><result status="valid" steps="155"/></proof>
  </goal>
  <goal name="VC def.6" expl="assertion" proved="true">
  <proof prover="0"><result status="valid" steps="712"/></proof>
  </goal>
  <goal name="VC def.7" expl="precondition">
  </goal>
  <goal name="VC def.8" expl="postcondition">
  </goal>
  <goal name="VC def.9" expl="postcondition" proved="true">
  <proof prover="0"><result status="valid" steps="160"/></proof>
  </goal>
 </transf>
 </goal>
</theory>
<theory name="Tlsf__block__types__round_address_up__subprogram_def">
 <goal name="VC def" expl="VC for def">
 <transf name="split_goal_wp_conj" >
  <goal name="VC def.0" expl="postcondition">
  </goal>
  <goal name="VC def.1" expl="precondition" proved="true">
  <proof prover="0"><result status="valid" steps="155"/></proof>
  </goal>
  <goal name="VC def.2" expl="precondition" proved="true">
  <proof prover="0"><result status="valid" steps="155"/></proof>
  </goal>
  <goal name="VC def.3" expl="precondition" proved="true">
  <proof prover="0"><result status="valid" steps="155"/></proof>
  </goal>
  <goal name="VC def.4" expl="precondition" proved="true">
  <proof prover="0"><result status="valid" steps="669"/></proof>
  </goal>
  <goal name="VC def.5" expl="precondition" proved="true">
  <proof prover="0"><result status="valid" steps="155"/></proof>
  </goal>
  <goal name="VC def.6" expl="assertion" proved="true">
  <proof prover="0"><result status="valid" steps="712"/></proof>
  </goal>
  <goal name="VC def.7" expl="precondition">
  </goal>
  <goal name="VC def.8" expl="postcondition">
  </goal>
  <goal name="VC def.9" expl="postcondition" proved="true">
  <proof prover="0"><result status="valid" steps="160"/></proof>
  </goal>
 </transf>
 </goal>
</theory>
<theory name="Tlsf__block__types__Oadd__subprogram_def">
 <goal name="VC def" expl="VC for def">
 <transf name="split_goal_wp_conj" >
  <goal name="VC def.0" expl="postcondition">
  </goal>
  <goal name="VC def.1" expl="precondition" proved="true">
  <proof prover="0"><result status="valid" steps="350"/></proof>
  </goal>
  <goal name="VC def.2" expl="postcondition">
  </goal>
  <goal name="VC def.3" expl="assertion" proved="true">
  <proof prover="0"><result status="valid" steps="162"/></proof>
  </goal>
  <goal name="VC def.4" expl="assertion" proved="true">
  <proof prover="0"><result status="valid" steps="162"/></proof>
  </goal>
  <goal name="VC def.5" expl="precondition" proved="true">
  <proof prover="0"><result status="valid" steps="355"/></proof>
  </goal>
  <goal name="VC def.6" expl="precondition">
  </goal>
  <goal name="VC def.7" expl="postcondition">
  </goal>
  <goal name="VC def.8" expl="precondition" proved="true">
  <proof prover="0"><result status="valid" steps="355"/></proof>
  </goal>
  <goal name="VC def.9" expl="precondition" proved="true">
  <proof prover="0"><result status="valid" steps="356"/></proof>
  </goal>
  <goal name="VC def.10" expl="assertion" proved="true">
  <proof prover="0"><result status="valid" steps="172"/></proof>
  </goal>
  <goal name="VC def.11" expl="precondition" proved="true">
  <proof prover="0"><result status="valid" steps="176"/></proof>
  </goal>
  <goal name="VC def.12" expl="assertion" proved="true">
  <proof prover="0"><result status="valid" steps="177"/></proof>
  </goal>
  <goal name="VC def.13" expl="precondition">
  </goal>
  <goal name="VC def.14" expl="postcondition">
  </goal>
  <goal name="VC def.15" expl="postcondition" proved="true">
  <proof prover="0"><result status="valid" steps="176"/></proof>
  </goal>
  <goal name="VC def.16" expl="postcondition" proved="true">
  <proof prover="0"><result status="valid" steps="176"/></proof>
  </goal>
 </transf>
 </goal>
</theory>
<theory name="Tlsf__block__types__Osubtract__subprogram_def">
 <goal name="VC def" expl="VC for def">
 <transf name="split_goal_wp_conj" >
  <goal name="VC def.0" expl="postcondition">
  </goal>
  <goal name="VC def.1" expl="precondition" proved="true">
  <proof prover="0"><result status="valid" steps="668"/></proof>
  </goal>
  <goal name="VC def.2" expl="postcondition">
  </goal>
  <goal name="VC def.3" expl="assertion" proved="true">
  <proof prover="0"><result status="valid" steps="158"/></proof>
  </goal>
  <goal name="VC def.4" expl="assertion" proved="true">
  <proof prover="0"><result status="valid" steps="669"/></proof>
  </goal>
  <goal name="VC def.5" expl="precondition" proved="true">
  <proof prover="0"><result status="valid" steps="351"/></proof>
  </goal>
  <goal name="VC def.6" expl="precondition">
  </goal>
  <goal name="VC def.7" expl="postcondition">
  </goal>
  <goal name="VC def.8" expl="precondition" proved="true">
  <proof prover="0"><result status="valid" steps="352"/></proof>
  </goal>
  <goal name="VC def.9" expl="precondition" proved="true">
  <proof prover="0"><result status="valid" steps="352"/></proof>
  </goal>
  <goal name="VC def.10" expl="assertion" proved="true">
  <proof prover="0"><result status="valid" steps="169"/></proof>
  </goal>
  <goal name="VC def.11" expl="precondition" proved="true">
  <proof prover="0"><result status="valid" steps="173"/></proof>
  </goal>
  <goal name="VC def.12" expl="assertion" proved="true">
  <proof prover="0"><result status="valid" steps="174"/></proof>
  </goal>
  <goal name="VC def.13" expl="precondition">
  </goal>
  <goal name="VC def.14" expl="postcondition">
  </goal>
  <goal name="VC def.15" expl="postcondition" proved="true">
  <proof prover="0"><result status="valid" steps="173"/></proof>
  </goal>
  <goal name="VC def.16" expl="postcondition" proved="true">
  <proof prover="0"><result status="valid" steps="173"/></proof>
  </goal>
 </transf>
 </goal>
</theory>
<theory name="Tlsf__block__types__aligned_addressPredicate__subprogram_def">
 <goal name="VC def" expl="VC for def">
 <transf name="split_goal_wp_conj" >
  <goal name="VC def.0" expl="postcondition">
  </goal>
  <goal name="VC def.1" expl="precondition">
  </goal>
  <goal name="VC def.2" expl="postcondition">
  </goal>
 </transf>
 </goal>
</theory>
<theory name="Tlsf__block__types__aligned_sizePredicate__subprogram_def">
 <goal name="VC def" expl="VC for def">
 <transf name="split_goal_wp_conj" >
  <goal name="VC def.0" expl="postcondition">
  </goal>
  <goal name="VC def.1" expl="precondition">
  </goal>
  <goal name="VC def.2" expl="postcondition">
  </goal>
 </transf>
 </goal>
</theory>
<theory name="Tlsf__block__types__free_blocks_listPredicate__subprogram_def">
 <goal name="VC def" expl="VC for def">
 <transf name="split_goal_wp_conj" >
  <goal name="VC def.0" expl="postcondition">
  </goal>
  <goal name="VC def.1" expl="postcondition">
  </goal>
 </transf>
 </goal>
</theory>
<theory name="Tlsf__block__types__is_free_list_empty__subprogram_def">
 <goal name="VC def" expl="VC for def">
 <transf name="split_goal_wp_conj" >
  <goal name="VC def.0" expl="postcondition">
  </goal>
  <goal name="VC def.1" expl="postcondition">
  </goal>
 </transf>
 </goal>
</theory>
<theory name="Tlsf__block__types__is_block_free__subprogram_def">
 <goal name="VC def" expl="VC for def">
 <transf name="split_goal_wp_conj" >
  <goal name="VC def.0" expl="postcondition">
  </goal>
  <goal name="VC def.1" expl="postcondition">
  </goal>
 </transf>
 </goal>
</theory>
<theory name="Tlsf__block__types__is_block_occupied__subprogram_def">
 <goal name="VC def" expl="VC for def">
 <transf name="split_goal_wp_conj" >
  <goal name="VC def.0" expl="postcondition">
  </goal>
  <goal name="VC def.1" expl="postcondition">
  </goal>
 </transf>
 </goal>
</theory>
<theory name="Tlsf__block__types__is_block_linked_to_free_list__subprogram_def">
 <goal name="VC def" expl="VC for def">
 <transf name="split_goal_wp_conj" >
  <goal name="VC def.0" expl="precondition">
  </goal>
  <goal name="VC def.1" expl="postcondition">
  </goal>
  <goal name="VC def.2" expl="precondition" proved="true">
  <proof prover="0"><result status="valid" steps="492"/></proof>
  </goal>
  <goal name="VC def.3" expl="precondition" proved="true">
  <proof prover="0"><result status="valid" steps="500"/></proof>
  </goal>
  <goal name="VC def.4" expl="precondition" proved="true">
  <proof prover="0"><result status="valid" steps="499"/></proof>
  </goal>
  <goal name="VC def.5" expl="precondition">
  </goal>
  <goal name="VC def.6" expl="postcondition">
  </goal>
  <goal name="VC def.7" expl="postcondition" proved="true">
  <proof prover="0"><result status="valid" steps="224"/></proof>
  </goal>
  <goal name="VC def.8" expl="postcondition" proved="true">
  <proof prover="0"><result status="valid" steps="862"/></proof>
  </goal>
  <goal name="VC def.9" expl="postcondition" proved="true">
  <proof prover="0"><result status="valid" steps="506"/></proof>
  </goal>
  <goal name="VC def.10" expl="postcondition" proved="true">
  <proof prover="0"><result status="valid" steps="224"/></proof>
  </goal>
 </transf>
 </goal>
</theory>
<theory name="Tlsf__block__types__is_block_last_in_free_list__subprogram_def">
 <goal name="VC def" expl="VC for def">
 <transf name="split_goal_wp_conj" >
  <goal name="VC def.0" expl="precondition">
  </goal>
  <goal name="VC def.1" expl="postcondition">
  </goal>
  <goal name="VC def.2" expl="precondition" proved="true">
  <proof prover="0"><result status="valid" steps="441"/></proof>
  </goal>
  <goal name="VC def.3" expl="precondition" proved="true">
  <proof prover="0"><result status="valid" steps="443"/></proof>
  </goal>
  <goal name="VC def.4" expl="precondition" proved="true">
  <proof prover="0"><result status="valid" steps="447"/></proof>
  </goal>
  <goal name="VC def.5" expl="precondition" proved="true">
  <proof prover="0"><result status="valid" steps="450"/></proof>
  </goal>
  <goal name="VC def.6" expl="precondition" proved="true">
  <proof prover="0"><result status="valid" steps="448"/></proof>
  </goal>
  <goal name="VC def.7" expl="precondition" proved="true">
  <proof prover="0"><result status="valid" steps="449"/></proof>
  </goal>
  <goal name="VC def.8" expl="postcondition">
  </goal>
  <goal name="VC def.9" expl="postcondition" proved="true">
  <proof prover="0"><result status="valid" steps="198"/></proof>
  </goal>
  <goal name="VC def.10" expl="postcondition" proved="true">
  <proof prover="0"><result status="valid" steps="216"/></proof>
  </goal>
  <goal name="VC def.11" expl="postcondition" proved="true">
  <proof prover="0"><result status="valid" steps="208"/></proof>
  </goal>
  <goal name="VC def.12" expl="postcondition" proved="true">
  <proof prover="0"><result status="valid" steps="198"/></proof>
  </goal>
 </transf>
 </goal>
</theory>
<theory name="Tlsf__block__types__changed_only_links_for_free_list__subprogram_def">
 <goal name="VC def" expl="VC for def">
 <transf name="split_goal_wp_conj" >
  <goal name="VC def.0" expl="postcondition">
  </goal>
  <goal name="VC def.1" expl="precondition">
  </goal>
  <goal name="VC def.2" expl="precondition">
  </goal>
  <goal name="VC def.3" expl="postcondition">
  </goal>
 </transf>
 </goal>
</theory>
<theory name="Tlsf__block__types__calculate_levels_indices__subprogram_def">
 <goal name="VC def" expl="VC for def">
 <transf name="split_goal_wp_conj" >
  <goal name="VC def.0" expl="postcondition">
  </goal>
  <goal name="VC def.1" expl="precondition" proved="true">
  <proof prover="0"><result status="valid" steps="23569"/></proof>
  </goal>
  <goal name="VC def.2" expl="precondition" proved="true">
  <proof prover="0"><result status="valid" steps="24730"/></proof>
  </goal>
  <goal name="VC def.3" expl="precondition" proved="true">
  <proof prover="0"><result status="valid" steps="329"/></proof>
  </goal>
  <goal name="VC def.4" expl="precondition" proved="true">
  <proof prover="0"><result status="valid" steps="24800"/></proof>
  </goal>
  <goal name="VC def.5" expl="postcondition">
  </goal>
  <goal name="VC def.6" expl="precondition" proved="true">
  <proof prover="0"><result status="valid" steps="23572"/></proof>
  </goal>
  <goal name="VC def.7" expl="precondition" proved="true">
  <proof prover="0"><result status="valid" steps="330"/></proof>
  </goal>
  <goal name="VC def.8" expl="precondition" proved="true">
  <proof prover="0"><result status="valid" steps="336"/></proof>
  </goal>
  <goal name="VC def.9" expl="precondition" proved="true">
  <proof prover="0"><result status="valid" steps="336"/></proof>
  </goal>
  <goal name="VC def.10" expl="precondition" proved="true">
  <proof prover="0"><result status="valid" steps="23602"/></proof>
  </goal>
  <goal name="VC def.11" expl="precondition" proved="true">
  <proof prover="0"><result status="valid" steps="338"/></proof>
  </goal>
  <goal name="VC def.12" expl="precondition" proved="true">
  <proof prover="0"><result status="valid" steps="338"/></proof>
  </goal>
  <goal name="VC def.13" expl="precondition" proved="true">
  <proof prover="0"><result status="valid" steps="338"/></proof>
  </goal>
  <goal name="VC def.14" expl="precondition" proved="true">
  <proof prover="0"><result status="valid" steps="24414"/></proof>
  </goal>
  <goal name="VC def.15" expl="postcondition">
  </goal>
  <goal name="VC def.16" expl="assertion" proved="true">
  <proof prover="0"><result status="valid" steps="340"/></proof>
  </goal>
  <goal name="VC def.17" expl="precondition" proved="true">
  <proof prover="0"><result status="valid" steps="24327"/></proof>
  </goal>
  <goal name="VC def.18" expl="precondition" proved="true">
  <proof prover="0"><result status="valid" steps="24328"/></proof>
  </goal>
  <goal name="VC def.19" expl="precondition" proved="true">
  <proof prover="0"><result status="valid" steps="344"/></proof>
  </goal>
  <goal name="VC def.20" expl="postcondition">
  </goal>
  <goal name="VC def.21" expl="precondition" proved="true">
  <proof prover="0"><result status="valid" steps="24114"/></proof>
  </goal>
  <goal name="VC def.22" expl="postcondition">
  </goal>
  <goal name="VC def.23" expl="precondition" proved="true">
  <proof prover="0"><result status="valid" steps="33537"/></proof>
  </goal>
  <goal name="VC def.24" expl="postcondition">
  </goal>
 </transf>
 </goal>
</theory>
<theory name="Tlsf__block__types__is_same_size_class__subprogram_def">
 <goal name="VC def" expl="VC for def">
 <transf name="split_goal_wp_conj" >
  <goal name="VC def.0" expl="postcondition">
  </goal>
  <goal name="VC def.1" expl="precondition" proved="true">
  <proof prover="0"><result status="valid" steps="693"/></proof>
  </goal>
  <goal name="VC def.2" expl="precondition" proved="true">
  <proof prover="0"><result status="valid" steps="704"/></proof>
  </goal>
  <goal name="VC def.3" expl="postcondition">
  </goal>
  <goal name="VC def.4" expl="postcondition">
  </goal>
  <goal name="VC def.5" expl="precondition" proved="true">
  <proof prover="0"><result status="valid" steps="695"/></proof>
  </goal>
  <goal name="VC def.6" expl="precondition" proved="true">
  <proof prover="0"><result status="valid" steps="704"/></proof>
  </goal>
  <goal name="VC def.7" expl="postcondition">
  </goal>
  <goal name="VC def.8" expl="postcondition">
  </goal>
  <goal name="VC def.9" expl="assertion" proved="true">
  <proof prover="0"><result status="valid" steps="156"/></proof>
  </goal>
  <goal name="VC def.10" expl="assertion" proved="true">
  <proof prover="0"><result status="valid" steps="172"/></proof>
  </goal>
  <goal name="VC def.11" expl="assertion" proved="true">
  <proof prover="0"><result status="valid" steps="156"/></proof>
  </goal>
  <goal name="VC def.12" expl="postcondition">
  </goal>
  <goal name="VC def.13" expl="assertion" proved="true">
  <proof prover="0"><result status="valid" steps="172"/></proof>
  </goal>
  <goal name="VC def.14" expl="assertion" proved="true">
  <proof prover="0"><result status="valid" steps="156"/></proof>
  </goal>
  <goal name="VC def.15" expl="assertion" proved="true">
  <proof prover="0"><result status="valid" steps="156"/></proof>
  </goal>
 </transf>
 </goal>
</theory>
<theory name="Tlsf__block__types__valid_addressPredicate__subprogram_def">
 <goal name="VC def" expl="VC for def">
 <transf name="split_goal_wp_conj" >
  <goal name="VC def.0" expl="postcondition">
  </goal>
  <goal name="VC def.1" expl="postcondition">
  </goal>
 </transf>
 </goal>
</theory>
<theory name="Tlsf__block__types__address_spacePredicate__subprogram_def">
 <goal name="VC def" expl="VC for def">
 <transf name="split_goal_wp_conj" >
  <goal name="VC def.0" expl="postcondition">
  </goal>
  <goal name="VC def.1" expl="postcondition">
  </goal>
 </transf>
 </goal>
</theory>
<theory name="Tlsf__block__types__bits_size__shifts__logic_right__subprogram_def">
 <goal name="VC def" expl="VC for def">
 <transf name="split_goal_wp_conj" >
  <goal name="VC def.0" expl="postcondition">
  </goal>
 </transf>
 </goal>
</theory>
<theory name="Tlsf__block__types__bits_size__shifts__logic_left__subprogram_def">
 <goal name="VC def" expl="VC for def">
 <transf name="split_goal_wp_conj" >
  <goal name="VC def.0" expl="postcondition">
  </goal>
 </transf>
 </goal>
</theory>
<theory name="Tlsf__block__types__bits_size__mask__shift__logic_right__subprogram_def">
 <goal name="VC def" expl="VC for def">
 <transf name="split_goal_wp_conj" >
  <goal name="VC def.0" expl="postcondition">
  </goal>
 </transf>
 </goal>
</theory>
<theory name="Tlsf__block__types__bits_size__mask__shift__logic_left__subprogram_def">
 <goal name="VC def" expl="VC for def">
 <transf name="split_goal_wp_conj" >
  <goal name="VC def.0" expl="postcondition">
  </goal>
 </transf>
 </goal>
</theory>
<theory name="Tlsf__block__types__bits_size__mask__make__subprogram_def">
 <goal name="VC def" expl="VC for def">
 <transf name="split_goal_wp_conj" >
  <goal name="VC def.0" expl="postcondition">
  </goal>
  <goal name="VC def.1" expl="precondition" proved="true">
  <proof prover="0"><result status="valid" steps="153"/></proof>
  </goal>
  <goal name="VC def.2" expl="precondition" proved="true">
  <proof prover="0"><result status="valid" steps="153"/></proof>
  </goal>
  <goal name="VC def.3" expl="postcondition">
  </goal>
  <goal name="VC def.4" expl="postcondition" proved="true">
  <proof prover="0"><result status="failure"/></proof>
  <proof prover="1"><result status="unknown" steps="32450110"/></proof>
  <proof prover="2"><result status="valid" steps="65604"/></proof>
  </goal>
 </transf>
 </goal>
</theory>
<theory name="Tlsf__block__types__bits_size__extract_pkg__shift__logic_right__subprogram_def">
 <goal name="VC def" expl="VC for def">
 <transf name="split_goal_wp_conj" >
  <goal name="VC def.0" expl="postcondition">
  </goal>
 </transf>
 </goal>
</theory>
<theory name="Tlsf__block__types__bits_size__extract_pkg__shift__logic_left__subprogram_def">
 <goal name="VC def" expl="VC for def">
 <transf name="split_goal_wp_conj" >
  <goal name="VC def.0" expl="postcondition">
  </goal>
 </transf>
 </goal>
</theory>
<theory name="Tlsf__block__types__bits_size__extract_pkg__mask__shift__logic_right__subprogram_def">
 <goal name="VC def" expl="VC for def">
 <transf name="split_goal_wp_conj" >
  <goal name="VC def.0" expl="postcondition">
  </goal>
 </transf>
 </goal>
</theory>
<theory name="Tlsf__block__types__bits_size__extract_pkg__mask__shift__logic_left__subprogram_def">
 <goal name="VC def" expl="VC for def">
 <transf name="split_goal_wp_conj" >
  <goal name="VC def.0" expl="postcondition">
  </goal>
 </transf>
 </goal>
</theory>
<theory name="Tlsf__block__types__bits_size__extract_pkg__mask__make__subprogram_def">
 <goal name="VC def" expl="VC for def">
 <transf name="split_goal_wp_conj" >
  <goal name="VC def.0" expl="postcondition">
  </goal>
  <goal name="VC def.1" expl="precondition" proved="true">
  <proof prover="0"><result status="valid" steps="153"/></proof>
  </goal>
  <goal name="VC def.2" expl="precondition" proved="true">
  <proof prover="0"><result status="valid" steps="153"/></proof>
  </goal>
  <goal name="VC def.3" expl="postcondition">
  </goal>
  <goal name="VC def.4" expl="postcondition" proved="true">
  <proof prover="0"><result status="failure"/></proof>
  <proof prover="1"><result status="unknown" steps="32450110"/></proof>
  <proof prover="2"><result status="valid" steps="65604"/></proof>
  </goal>
 </transf>
 </goal>
</theory>
<theory name="Tlsf__block__types__bits_size__extract_pkg__extract__subprogram_def">
 <goal name="VC def" expl="VC for def">
 <transf name="split_goal_wp_conj" >
  <goal name="VC def.0" expl="postcondition">
  </goal>
  <goal name="VC def.1" expl="precondition" proved="true">
  <proof prover="0"><result status="valid" steps="660"/></proof>
  </goal>
  <goal name="VC def.2" expl="precondition" proved="true">
  <proof prover="0"><result status="valid" steps="154"/></proof>
  </goal>
  <goal name="VC def.3" expl="precondition" proved="true">
  <proof prover="0"><result status="valid" steps="345"/></proof>
  </goal>
  <goal name="VC def.4" expl="precondition" proved="true">
  <proof prover="0"><result status="valid" steps="938"/></proof>
  </goal>
  <goal name="VC def.5" expl="precondition" proved="true">
  <proof prover="0"><result status="valid" steps="939"/></proof>
  </goal>
  <goal name="VC def.6" expl="precondition" proved="true">
  <proof prover="0"><result status="valid" steps="168"/></proof>
  </goal>
  <goal name="VC def.7" expl="precondition" proved="true">
  <proof prover="0"><result status="valid" steps="168"/></proof>
  </goal>
  <goal name="VC def.8" expl="precondition" proved="true">
  <proof prover="0"><result status="valid" steps="364"/></proof>
  </goal>
  <goal name="VC def.9" expl="precondition" proved="true">
  <proof prover="0"><result status="valid" steps="1086"/></proof>
  </goal>
  <goal name="VC def.10" expl="precondition" proved="true">
  <proof prover="0"><result status="valid" steps="1037"/></proof>
  </goal>
  <goal name="VC def.11" expl="precondition" proved="true">
  <proof prover="0"><result status="valid" steps="670"/></proof>
  </goal>
  <goal name="VC def.12" expl="postcondition">
  </goal>
  <goal name="VC def.13" expl="postcondition" proved="true">
  <proof prover="0"><result status="valid" steps="168"/></proof>
  </goal>
  <goal name="VC def.14" expl="postcondition" proved="true">
  <proof prover="0"><result status="failure"/></proof>
  <proof prover="1"><result status="valid" steps="79057"/></proof>
  <proof prover="2" obsolete="true"><result status="unknown" steps="71221"/></proof>
  <proof prover="3" obsolete="true"><result status="unknown" steps="139302"/></proof>
  </goal>
 </transf>
 </goal>
</theory>
<theory name="Tlsf__block__types__bits_size__search__shift__logic_right__subprogram_def">
 <goal name="VC def" expl="VC for def">
 <transf name="split_goal_wp_conj" >
  <goal name="VC def.0" expl="postcondition">
  </goal>
 </transf>
 </goal>
</theory>
<theory name="Tlsf__block__types__bits_size__search__shift__logic_left__subprogram_def">
 <goal name="VC def" expl="VC for def">
 <transf name="split_goal_wp_conj" >
  <goal name="VC def.0" expl="postcondition">
  </goal>
 </transf>
 </goal>
</theory>
<theory name="Tlsf__block__types__bits_size__search__mask__shift__logic_right__subprogram_def">
 <goal name="VC def" expl="VC for def">
 <transf name="split_goal_wp_conj" >
  <goal name="VC def.0" expl="postcondition">
  </goal>
 </transf>
 </goal>
</theory>
<theory name="Tlsf__block__types__bits_size__search__mask__shift__logic_left__subprogram_def">
 <goal name="VC def" expl="VC for def">
 <transf name="split_goal_wp_conj" >
  <goal name="VC def.0" expl="postcondition">
  </goal>
 </transf>
 </goal>
</theory>
<theory name="Tlsf__block__types__bits_size__search__mask__make__subprogram_def">
 <goal name="VC def" expl="VC for def">
 <transf name="split_goal_wp_conj" >
  <goal name="VC def.0" expl="postcondition">
  </goal>
  <goal name="VC def.1" expl="precondition" proved="true">
  <proof prover="0"><result status="valid" steps="153"/></proof>
  </goal>
  <goal name="VC def.2" expl="precondition" proved="true">
  <proof prover="0"><result status="valid" steps="153"/></proof>
  </goal>
  <goal name="VC def.3" expl="postcondition">
  </goal>
  <goal name="VC def.4" expl="postcondition" proved="true">
  <proof prover="0"><result status="failure"/></proof>
  <proof prover="1"><result status="unknown" steps="32450110"/></proof>
  <proof prover="2"><result status="valid" steps="65604"/></proof>
  </goal>
 </transf>
 </goal>
</theory>
<theory name="Tlsf__block__types__bits_size__search__most_significant_bit__subprogram_def">
 <goal name="VC def" expl="VC for def">
 <transf name="split_goal_wp_conj" >
  <goal name="VC def.0" expl="postcondition">
  </goal>
  <goal name="VC def.1" expl="precondition" proved="true">
  <proof prover="0"><result status="valid" steps="156"/></proof>
  </goal>
  <goal name="VC def.2" expl="precondition" proved="true">
  <proof prover="0"><result status="valid" steps="156"/></proof>
  </goal>
  <goal name="VC def.3" expl="postcondition">
  </goal>
 </transf>
 </goal>
</theory>
<theory name="Tlsf__block__types__is_aligned__is_aligned_size__subprogram_def">
 <goal name="VC def" expl="VC for def">
 <transf name="split_goal_wp_conj" >
  <goal name="VC def.0" expl="postcondition">
  </goal>
  <goal name="VC def.1" expl="postcondition">
  </goal>
  <goal name="VC def.2" expl="postcondition">
  </goal>
  <goal name="VC def.3" expl="check" proved="true">
  <proof prover="0"><result status="valid" steps="357"/></proof>
  </goal>
  <goal name="VC def.4" expl="check" proved="true">
  <proof prover="0"><result status="valid" steps="357"/></proof>
  </goal>
  <goal name="VC def.5" expl="postcondition">
  </goal>
  <goal name="VC def.6" expl="postcondition">
  </goal>
  <goal name="VC def.7" expl="postcondition">
  </goal>
  <goal name="VC def.8" expl="assertion" proved="true">
  <proof prover="0"><result status="valid" steps="155"/></proof>
  </goal>
  <goal name="VC def.9" expl="assertion" proved="true">
  <proof prover="0"><result status="valid" steps="158"/></proof>
  </goal>
  <goal name="VC def.10" expl="assertion" proved="true">
  <proof prover="0"><result status="valid" steps="155"/></proof>
  </goal>
  <goal name="VC def.11" expl="postcondition">
  </goal>
  <goal name="VC def.12" expl="assertion" proved="true">
  <proof prover="0"><result status="valid" steps="357"/></proof>
  </goal>
  <goal name="VC def.13" expl="assertion" proved="true">
  <proof prover="0"><result status="valid" steps="155"/></proof>
  </goal>
  <goal name="VC def.14" expl="assertion" proved="true">
  <proof prover="0"><result status="valid" steps="155"/></proof>
  </goal>
 </transf>
 </goal>
</theory>
<theory name="Tlsf__block__types__is_aligned__2__is_aligned_addr__subprogram_def">
 <goal name="VC def" expl="VC for def">
 <transf name="split_goal_wp_conj" >
  <goal name="VC def.0" expl="postcondition">
  </goal>
  <goal name="VC def.1" expl="postcondition">
  </goal>
  <goal name="VC def.2" expl="postcondition">
  </goal>
  <goal name="VC def.3" expl="check" proved="true">
  <proof prover="0"><result status="valid" steps="357"/></proof>
  </goal>
  <goal name="VC def.4" expl="check" proved="true">
  <proof prover="0"><result status="valid" steps="357"/></proof>
  </goal>
  <goal name="VC def.5" expl="postcondition">
  </goal>
  <goal name="VC def.6" expl="postcondition">
  </goal>
  <goal name="VC def.7" expl="postcondition">
  </goal>
  <goal name="VC def.8" expl="assertion" proved="true">
  <proof prover="0"><result status="valid" steps="155"/></proof>
  </goal>
  <goal name="VC def.9" expl="assertion" proved="true">
  <proof prover="0"><result status="valid" steps="158"/></proof>
  </goal>
  <goal name="VC def.10" expl="assertion" proved="true">
  <proof prover="0"><result status="valid" steps="155"/></proof>
  </goal>
  <goal name="VC def.11" expl="postcondition">
  </goal>
  <goal name="VC def.12" expl="assertion" proved="true">
  <proof prover="0"><result status="valid" steps="357"/></proof>
  </goal>
  <goal name="VC def.13" expl="assertion" proved="true">
  <proof prover="0"><result status="valid" steps="155"/></proof>
  </goal>
  <goal name="VC def.14" expl="assertion" proved="true">
  <proof prover="0"><result status="valid" steps="155"/></proof>
  </goal>
 </transf>
 </goal>
</theory>
<theory name="Tlsf__block__types__round_size_up__is_aligned_val__subprogram_def">
 <goal name="VC def" expl="VC for def">
 <transf name="split_goal_wp_conj" >
  <goal name="VC def.0" expl="postcondition">
  </goal>
  <goal name="VC def.1" expl="postcondition">
  </goal>
  <goal name="VC def.2" expl="postcondition">
  </goal>
  <goal name="VC def.3" expl="check" proved="true">
  <proof prover="0"><result status="valid" steps="357"/></proof>
  </goal>
  <goal name="VC def.4" expl="check" proved="true">
  <proof prover="0"><result status="valid" steps="357"/></proof>
  </goal>
  <goal name="VC def.5" expl="postcondition">
  </goal>
  <goal name="VC def.6" expl="postcondition">
  </goal>
  <goal name="VC def.7" expl="postcondition">
  </goal>
  <goal name="VC def.8" expl="assertion" proved="true">
  <proof prover="0"><result status="valid" steps="155"/></proof>
  </goal>
  <goal name="VC def.9" expl="assertion" proved="true">
  <proof prover="0"><result status="valid" steps="158"/></proof>
  </goal>
  <goal name="VC def.10" expl="assertion" proved="true">
  <proof prover="0"><result status="valid" steps="155"/></proof>
  </goal>
  <goal name="VC def.11" expl="postcondition">
  </goal>
  <goal name="VC def.12" expl="assertion" proved="true">
  <proof prover="0"><result status="valid" steps="357"/></proof>
  </goal>
  <goal name="VC def.13" expl="assertion" proved="true">
  <proof prover="0"><result status="valid" steps="155"/></proof>
  </goal>
  <goal name="VC def.14" expl="assertion" proved="true">
  <proof prover="0"><result status="valid" steps="155"/></proof>
  </goal>
 </transf>
 </goal>
</theory>
<theory name="Tlsf__block__types__round_size_up__round__subprogram_def">
 <goal name="VC def" expl="VC for def">
 <transf name="split_goal_wp_conj" >
  <goal name="VC def.0" expl="postcondition">
  </goal>
  <goal name="VC def.1" expl="postcondition">
  </goal>
  <goal name="VC def.2" expl="assertion" proved="true">
  <proof prover="0"><result status="valid" steps="164"/></proof>
  </goal>
  <goal name="VC def.3" expl="postcondition">
  </goal>
  <goal name="VC def.4" expl="assertion" proved="true">
  <proof prover="0"><result status="valid" steps="695"/></proof>
  </goal>
  <goal name="VC def.5" expl="precondition" proved="true">
  <proof prover="0"><result status="valid" steps="841"/></proof>
  </goal>
  <goal name="VC def.6" expl="precondition" proved="true">
  <proof prover="0"><result status="failure"/></proof>
  <proof prover="1"><result status="valid" steps="550"/></proof>
  </goal>
  <goal name="VC def.7" expl="precondition" proved="true">
  <proof prover="0"><result status="valid" steps="160"/></proof>
  </goal>
  <goal name="VC def.8" expl="precondition" proved="true">
  <proof prover="0"><result status="valid" steps="381"/></proof>
  </goal>
  <goal name="VC def.9" expl="precondition" proved="true">
  <proof prover="0"><result status="valid" steps="758"/></proof>
  </goal>
  <goal name="VC def.10" expl="postcondition" proved="true">
  <proof prover="0"><result status="valid" steps="160"/></proof>
  </goal>
  <goal name="VC def.11" expl="assertion" proved="true">
  <proof prover="0"><result status="failure"/></proof>
  <proof prover="1"><result status="valid" steps="9095"/></proof>
  </goal>
  <goal name="VC def.12" expl="precondition" proved="true">
  <proof prover="0"><result status="valid" steps="160"/></proof>
  </goal>
  <goal name="VC def.13" expl="precondition" proved="true">
  <proof prover="0"><result status="valid" steps="392"/></proof>
  </goal>
  <goal name="VC def.14" expl="precondition" proved="true">
  <proof prover="0"><result status="valid" steps="929"/></proof>
  </goal>
  <goal name="VC def.15" expl="postcondition" proved="true">
  <proof prover="0"><result status="valid" steps="160"/></proof>
  </goal>
  <goal name="VC def.16" expl="postcondition" proved="true">
  <proof prover="0"><result status="valid" steps="784"/></proof>
  </goal>
  <goal name="VC def.17" expl="postcondition" proved="true">
  <proof prover="0"><result status="valid" steps="1087"/></proof>
  </goal>
 </transf>
 </goal>
</theory>
<theory name="Tlsf__block__types__round_address_up__is_aligned_val__subprogram_def">
 <goal name="VC def" expl="VC for def">
 <transf name="split_goal_wp_conj" >
  <goal name="VC def.0" expl="postcondition">
  </goal>
  <goal name="VC def.1" expl="postcondition">
  </goal>
  <goal name="VC def.2" expl="postcondition">
  </goal>
  <goal name="VC def.3" expl="check" proved="true">
  <proof prover="0"><result status="valid" steps="357"/></proof>
  </goal>
  <goal name="VC def.4" expl="check" proved="true">
  <proof prover="0"><result status="valid" steps="357"/></proof>
  </goal>
  <goal name="VC def.5" expl="postcondition">
  </goal>
  <goal name="VC def.6" expl="postcondition">
  </goal>
  <goal name="VC def.7" expl="postcondition">
  </goal>
  <goal name="VC def.8" expl="assertion" proved="true">
  <proof prover="0"><result status="valid" steps="155"/></proof>
  </goal>
  <goal name="VC def.9" expl="assertion" proved="true">
  <proof prover="0"><result status="valid" steps="158"/></proof>
  </goal>
  <goal name="VC def.10" expl="assertion" proved="true">
  <proof prover="0"><result status="valid" steps="155"/></proof>
  </goal>
  <goal name="VC def.11" expl="postcondition">
  </goal>
  <goal name="VC def.12" expl="assertion" proved="true">
  <proof prover="0"><result status="valid" steps="357"/></proof>
  </goal>
  <goal name="VC def.13" expl="assertion" proved="true">
  <proof prover="0"><result status="valid" steps="155"/></proof>
  </goal>
  <goal name="VC def.14" expl="assertion" proved="true">
  <proof prover="0"><result status="valid" steps="155"/></proof>
  </goal>
 </transf>
 </goal>
</theory>
<theory name="Tlsf__block__types__round_address_up__round__subprogram_def">
 <goal name="VC def" expl="VC for def">
 <transf name="split_goal_wp_conj" >
  <goal name="VC def.0" expl="postcondition">
  </goal>
  <goal name="VC def.1" expl="postcondition">
  </goal>
  <goal name="VC def.2" expl="assertion" proved="true">
  <proof prover="0"><result status="valid" steps="164"/></proof>
  </goal>
  <goal name="VC def.3" expl="postcondition">
  </goal>
  <goal name="VC def.4" expl="assertion" proved="true">
  <proof prover="0"><result status="valid" steps="695"/></proof>
  </goal>
  <goal name="VC def.5" expl="precondition" proved="true">
  <proof prover="0"><result status="valid" steps="841"/></proof>
  </goal>
  <goal name="VC def.6" expl="precondition" proved="true">
  <proof prover="0"><result status="failure"/></proof>
  <proof prover="1"><result status="valid" steps="550"/></proof>
  </goal>
  <goal name="VC def.7" expl="precondition" proved="true">
  <proof prover="0"><result status="valid" steps="160"/></proof>
  </goal>
  <goal name="VC def.8" expl="precondition" proved="true">
  <proof prover="0"><result status="valid" steps="381"/></proof>
  </goal>
  <goal name="VC def.9" expl="precondition" proved="true">
  <proof prover="0"><result status="valid" steps="758"/></proof>
  </goal>
  <goal name="VC def.10" expl="postcondition" proved="true">
  <proof prover="0"><result status="valid" steps="160"/></proof>
  </goal>
  <goal name="VC def.11" expl="assertion" proved="true">
  <proof prover="0"><result status="failure"/></proof>
  <proof prover="1"><result status="valid" steps="9095"/></proof>
  </goal>
  <goal name="VC def.12" expl="precondition" proved="true">
  <proof prover="0"><result status="valid" steps="160"/></proof>
  </goal>
  <goal name="VC def.13" expl="precondition" proved="true">
  <proof prover="0"><result status="valid" steps="392"/></proof>
  </goal>
  <goal name="VC def.14" expl="precondition" proved="true">
  <proof prover="0"><result status="valid" steps="929"/></proof>
  </goal>
  <goal name="VC def.15" expl="postcondition" proved="true">
  <proof prover="0"><result status="valid" steps="160"/></proof>
  </goal>
  <goal name="VC def.16" expl="postcondition" proved="true">
  <proof prover="0"><result status="valid" steps="783"/></proof>
  </goal>
  <goal name="VC def.17" expl="postcondition" proved="true">
  <proof prover="0"><result status="valid" steps="1087"/></proof>
  </goal>
 </transf>
 </goal>
</theory>
<theory name="Tlsf__block__types__calculate_levels_indices__msb_axiom__result_is_correct__subprogram_def">
 <goal name="VC def" expl="VC for def">
 <transf name="split_goal_wp_conj" >
  <goal name="VC def.0" expl="precondition" proved="true">
  <proof prover="0"><result status="valid" steps="153"/></proof>
  </goal>
  <goal name="VC def.1" expl="postcondition">
  </goal>
 </transf>
 </goal>
</theory>
<theory name="Tlsf__block__types__calculate_levels_indices__msb_axiom__order_preservation_value_to_index__subprogram_def">
 <goal name="VC def" expl="VC for def">
 <transf name="split_goal_wp_conj" >
  <goal name="VC def.0" expl="precondition" proved="true">
  <proof prover="0"><result status="valid" steps="156"/></proof>
  </goal>
  <goal name="VC def.1" expl="precondition" proved="true">
  <proof prover="0"><result status="valid" steps="162"/></proof>
  </goal>
  <goal name="VC def.2" expl="postcondition">
  </goal>
 </transf>
 </goal>
</theory>
<theory name="Tlsf__block__types__calculate_levels_indices__msb_axiom__order_preservation_index_to_value__subprogram_def">
 <goal name="VC def" expl="VC for def">
 <transf name="split_goal_wp_conj" >
  <goal name="VC def.0" expl="precondition" proved="true">
  <proof prover="0"><result status="valid" steps="156"/></proof>
  </goal>
  <goal name="VC def.1" expl="precondition" proved="true">
  <proof prover="0"><result status="valid" steps="162"/></proof>
  </goal>
  <goal name="VC def.2" expl="postcondition">
  </goal>
 </transf>
 </goal>
</theory>
</file>
</why3session>
